v1/__init__.py
v1/client.py
cxreports_api_client-0.0.3.dist-info/METADATA
cxreports_api_client-0.0.3.dist-info/WHEEL
cxreports_api_client-0.0.3.dist-info/top_level.txt
cxreports_api_client-0.0.3.dist-info/RECORD
