Metadata-Version: 2.2
Name: cxreports_api_client
Version: 0.0.3
Summary: Connect to CxReports API from your application.
Home-page: https://github.com/cx-reports/api-client-python
Author: Codaxy
Author-email: support@cx-reports.com
License: MIT
Classifier: Programming Language :: Python :: 3
Classifier: License :: OSI Approved :: MIT License
Classifier: Operating System :: OS Independent
Requires-Python: >=3.0
Requires-Dist: requests
Dynamic: author
Dynamic: author-email
Dynamic: classifier
Dynamic: description
Dynamic: description-content-type
Dynamic: home-page
Dynamic: license
Dynamic: requires-dist
Dynamic: requires-python
Dynamic: summary
